osmolytes/__init__.py
osmolytes/energy.py
osmolytes/main.py
osmolytes/pqr.py
osmolytes/sasa.py
osmolytes/data/creamer-areas.yaml
osmolytes/data/denatured-areas.yaml
osmolytes/data/transfer-energies.yaml
osmolytes/data/tripeptide-areas.yaml
osmolytes-1.3.0.dist-info/LICENSE
osmolytes-1.3.0.dist-info/METADATA
osmolytes-1.3.0.dist-info/WHEEL
osmolytes-1.3.0.dist-info/entry_points.txt
osmolytes-1.3.0.dist-info/top_level.txt
osmolytes-1.3.0.dist-info/RECORD
